MANIFEST.in
README.txt
setup.py
collective/__init__.py
collective/__init__.pyc
collective.js.abcjs.egg-info/PKG-INFO
collective.js.abcjs.egg-info/SOURCES.txt
collective.js.abcjs.egg-info/dependency_links.txt
collective.js.abcjs.egg-info/entry_points.txt
collective.js.abcjs.egg-info/namespace_packages.txt
collective.js.abcjs.egg-info/not-zip-safe
collective.js.abcjs.egg-info/requires.txt
collective.js.abcjs.egg-info/top_level.txt
collective/js/__init__.py
collective/js/__init__.pyc
collective/js/abcjs/__init__.py
collective/js/abcjs/configure.zcml
collective/js/abcjs/interfaces.py
collective/js/abcjs/tests.py
collective/js/abcjs/version.txt
collective/js/abcjs/examples/__init__.py
collective/js/abcjs/examples/abcjs_example.pt
collective/js/abcjs/examples/abcjs_example.py
collective/js/abcjs/examples/configure.zcml
collective/js/abcjs/profiles/default/jsregistry.xml
collective/js/abcjs/profiles/default/metadata.xml
collective/js/abcjs/resources/abcjs_basic_1.10-min.js
collective/js/abcjs/resources/abcjs_basic_noraphael_1.10-min.js
collective/js/abcjs/resources/abcjs_editor_1.10-min.js
collective/js/abcjs/resources/abcjs_editor_noraphael_1.10-min.js
collective/js/abcjs/resources/abcjs_plugin_1.10-min.js
collective/js/abcjs/resources/abcjs_plugin_1.10.user.js
collective/js/abcjs/resources/abcjs_plugin_nojquery_1.10-min.js
collective/js/abcjs/resources/abcjs_plugin_noraphael_nojquery_1.10-min.js
docs/HISTORY.txt
docs/INSTALL.txt
docs/LICENSE.GPL
docs/LICENSE.txt